biofilter/__init__.py
biofilter/alembic/README
biofilter/alembic/env.py
biofilter/alembic/script.py.mako
biofilter/alembic/versions/0c242ad16a44_3_0_1_base_schema.py
biofilter/biofilter.py
biofilter/bkps/extract_loki.py
biofilter/bkps/loki_models.py
biofilter/bkps/variants_version_full/dtp_dbsnp_V3.old
biofilter/bkps/variants_version_full/dtp_dbsnp_v2.old
biofilter/bkps/variants_version_full/initial_allele_types.json
biofilter/bkps/variants_version_full/initial_variant_types.json
biofilter/bkps/variants_version_full/variants_models_V1.py
biofilter/cli.py
biofilter/core/__init__.py
biofilter/core/mixins/__init__.py
biofilter/core/mixins/get_data_mixin.py
biofilter/core/settings_manager.py
biofilter/db/__init__.py
biofilter/db/base.py
biofilter/db/create_db_mixin.py
biofilter/db/database.py
biofilter/db/models/__init__.py
biofilter/db/models/model_chemicals.py
biofilter/db/models/model_config.py
biofilter/db/models/model_curation.py
biofilter/db/models/model_diseases.py
biofilter/db/models/model_entities.py
biofilter/db/models/model_etl.py
biofilter/db/models/model_genes.py
biofilter/db/models/model_go.py
biofilter/db/models/model_pathways.py
biofilter/db/models/model_proteins.py
biofilter/db/models/model_variants.py
biofilter/db/models/models_info.json
biofilter/db/seed/initial_config.json
biofilter/db/seed/initial_data_sources.json
biofilter/db/seed/initial_entity_group.json
biofilter/db/seed/initial_entity_relationship_types.json
biofilter/db/seed/initial_etl_processes.json
biofilter/db/seed/initial_genome_assemblies.json
biofilter/db/seed/initial_metadata.json
biofilter/db/seed/initial_omic_status.json
biofilter/db/seed/initial_source_systems.json
biofilter/db/types.py
biofilter/etl/__init__.py
biofilter/etl/conflict_manager.py
biofilter/etl/dtps/__init__.py
biofilter/etl/dtps/devs/dtp_variant_ncbi__multiproc__.py
biofilter/etl/dtps/devs/dtp_variant_ncbi_bkp1.py
biofilter/etl/dtps/devs/worker_dbsnp__multiproc__.py
biofilter/etl/dtps/dtp_biogrid.py
biofilter-3.2.0.dist-info/METADATA
biofilter-3.2.0.dist-info/WHEEL
biofilter-3.2.0.dist-info/entry_points.txt
biofilter-3.2.0.dist-info/RECORD
