Metadata-Version: 2.1
Name: biofilter
Version: 3.2.0
Summary: Biofilter3R: cloud-ready biological knowledge system
Home-page: https://ritchielab.org
License: MIT
Author: Andre Rico
Author-email: andreluis.rico@pennmedicine.upenn.edu
Requires-Python: >=3.10,<4.0
Classifier: License :: OSI Approved :: MIT License
Classifier: Programming Language :: Python :: 3
Classifier: Programming Language :: Python :: 3.10
Classifier: Programming Language :: Python :: 3.11
Classifier: Programming Language :: Python :: 3.12
Requires-Dist: aiosqlite (>=0.21.0,<0.22.0)
Requires-Dist: alembic (>=1.16.4,<2.0.0)
Requires-Dist: apsw (==3.46.1.0)
Requires-Dist: click (==8.1.7)
Requires-Dist: colorama (>=0.4.6,<0.5.0)
Requires-Dist: duckdb (>=1.4.0,<2.0.0)
Requires-Dist: iniconfig (==2.0.0)
Requires-Dist: notebook (>=7.4.6,<8.0.0)
Requires-Dist: openpyxl (>=3.1.5,<4.0.0)
Requires-Dist: packaging (==24.1)
Requires-Dist: pandas (>=2.2.3,<3.0.0)
Requires-Dist: platformdirs (==4.3.6)
Requires-Dist: pluggy (==1.5.0)
Requires-Dist: psutil (>=6.1.1,<7.0.0)
Requires-Dist: psycopg2-binary (>=2.9.10,<3.0.0)
Requires-Dist: pyarrow (>=19.0.1,<20.0.0)
Requires-Dist: requests (>=2.32.4,<3.0.0)
Requires-Dist: sqlalchemy (>=2.0.37,<3.0.0)
Requires-Dist: toml (>=0.10.2,<0.11.0)
Requires-Dist: tqdm (>=4.67.1,<5.0.0)
Requires-Dist: wget (>=3.2,<4.0)
